unstructured_paddleocr/__init__.py
unstructured_paddleocr/unstructured_paddleocr.py
unstructured_paddleocr/ppocr/__init__.py
unstructured_paddleocr/ppocr/data/__init__.py
unstructured_paddleocr/ppocr/data/collate_fn.py
unstructured_paddleocr/ppocr/data/latexocr_dataset.py
unstructured_paddleocr/ppocr/data/multi_scale_sampler.py
unstructured_paddleocr/ppocr/data/pgnet_dataset.py
unstructured_paddleocr/ppocr/data/pubtab_dataset.py
unstructured_paddleocr/ppocr/data/simple_dataset.py
unstructured_paddleocr/ppocr/data/imaug/ColorJitter.py
unstructured_paddleocr/ppocr/data/imaug/__init__.py
unstructured_paddleocr/ppocr/data/imaug/abinet_aug.py
unstructured_paddleocr/ppocr/data/imaug/copy_paste.py
unstructured_paddleocr/ppocr/data/imaug/ct_process.py
unstructured_paddleocr/ppocr/data/imaug/drrg_targets.py
unstructured_paddleocr/ppocr/data/imaug/east_process.py
unstructured_paddleocr/ppocr/data/imaug/fce_aug.py
unstructured_paddleocr/ppocr/data/imaug/fce_targets.py
unstructured_paddleocr/ppocr/data/imaug/iaa_augment.py
unstructured_paddleocr/ppocr/data/imaug/label_ops.py
unstructured_paddleocr/ppocr/data/imaug/latex_ocr_aug.py
unstructured_paddleocr/ppocr/data/imaug/make_border_map.py
unstructured_paddleocr/ppocr/data/imaug/make_pse_gt.py
unstructured_paddleocr/ppocr/data/imaug/make_shrink_map.py
unstructured_paddleocr/ppocr/data/imaug/operators.py
unstructured_paddleocr/ppocr/data/imaug/pg_process.py
unstructured_paddleocr/ppocr/data/imaug/randaugment.py
unstructured_paddleocr/ppocr/data/imaug/random_crop_data.py
unstructured_paddleocr/ppocr/data/imaug/rec_img_aug.py
unstructured_paddleocr/ppocr/data/imaug/sast_process.py
unstructured_paddleocr/ppocr/data/imaug/ssl_img_aug.py
unstructured_paddleocr/ppocr/data/imaug/table_ops.py
unstructured_paddleocr/ppocr/data/imaug/unimernet_aug.py
unstructured_paddleocr/ppocr/data/imaug/frost_img/frost1.jpg
unstructured_paddleocr/ppocr/data/imaug/frost_img/frost2.png
unstructured_paddleocr/ppocr/data/imaug/frost_img/frost3.png
unstructured_paddleocr-2.10.0.dist-info/LICENSE
unstructured_paddleocr-2.10.0.dist-info/METADATA
unstructured_paddleocr-2.10.0.dist-info/WHEEL
unstructured_paddleocr-2.10.0.dist-info/entry_points.txt
unstructured_paddleocr-2.10.0.dist-info/top_level.txt
unstructured_paddleocr-2.10.0.dist-info/RECORD
